a2pcej/__init__.py
a2pcej/__main__.py
a2pcej/_version.py
a2pcej/a2pcej.py
a2pcej/phonetics.py
a2pcej-0.2.4.dist-info/licenses/LICENSE.txt
a2pcej-0.2.4.dist-info/METADATA
a2pcej-0.2.4.dist-info/WHEEL
a2pcej-0.2.4.dist-info/entry_points.txt
a2pcej-0.2.4.dist-info/top_level.txt
a2pcej-0.2.4.dist-info/RECORD
