Metadata-Version: 2.4
Name: a2pcej
Version: 0.2.4
Summary: a2pcej, convert Alphabet to Phonetic Code in English and Japanese.
Author-email: Katsuya SAITO <hello@skatsuya.com>
License-Expression: MIT
Project-URL: Homepage, https://github.com/kacchan822/a2pcej
Project-URL: Repository, https://github.com/kacchan822/a2pcej
Project-URL: Issues, https://github.com/kacchan822/a2pcej/issues
Keywords: alphabet,katakana,phonetic code
Classifier: Development Status :: 3 - Alpha
Classifier: Environment :: Console
Classifier: Intended Audience :: Developers
Classifier: Intended Audience :: System Administrators
Classifier: Intended Audience :: Customer Service
Classifier: Natural Language :: Japanese
Classifier: Natural Language :: English
Classifier: Operating System :: POSIX
Classifier: Programming Language :: Python :: 3
Classifier: Programming Language :: Python :: 3.8
Classifier: Programming Language :: Python :: 3.9
Classifier: Programming Language :: Python :: 3.10
Classifier: Programming Language :: Python :: 3.11
Classifier: Programming Language :: Python :: 3.12
Classifier: Topic :: Software Development
Classifier: Topic :: Text Processing
Classifier: Topic :: Utilities
Requires-Python: >=3.8
License-File: LICENSE.txt
Provides-Extra: dev
Requires-Dist: pytest>=7.0; extra == "dev"
Requires-Dist: pytest-cov; extra == "dev"
Requires-Dist: black; extra == "dev"
Requires-Dist: flake8; extra == "dev"
Requires-Dist: mypy; extra == "dev"
Requires-Dist: isort; extra == "dev"
Requires-Dist: twine; extra == "dev"
Requires-Dist: build; extra == "dev"
Dynamic: license-file
